dvha/__init__.py
dvha/_version.py
dvha/main.py
dvha/options.py
dvha/paths.py
dvha/db/__init__.py
dvha/db/create_tables.sql
dvha/db/create_tables_sqlite.sql
dvha/db/dicom_parser.py
dvha/db/sql_columns.py
dvha/db/sql_connector.py
dvha/db/sql_to_python.py
dvha/db/update.py
dvha/dialogs/__init__.py
dvha/dialogs/database.py
dvha/dialogs/export.py
dvha/dialogs/main.py
dvha/dialogs/roi_map.py
dvha/models/__init__.py
dvha/models/control_chart.py
dvha/models/correlation.py
dvha/models/data_table.py
dvha/models/database_editor.py
dvha/models/dicom_tree_builder.py
dvha/models/dvh.py
dvha/models/endpoint.py
dvha/models/import_dicom.py
dvha/models/machine_learning.py
dvha/models/plot.py
dvha/models/queried_data.py
dvha/models/rad_bio.py
dvha/models/regression.py
dvha/models/roi_map.py
dvha/models/spreadsheet.py
dvha/models/stats_data_editor.py
dvha/models/time_series.py
dvha/resources/LICENSE.txt
dvha/resources/TG263_Nomenclature_Worksheet_20170815.csv
dvha/resources/logo.png
dvha/resources/icons/dvha.icns
dvha/resources/icons/dvha_new.ico
dvha/resources/icons/error.png
dvha/resources/icons/icon_custom_X.png
dvha/resources/icons/icon_custom_Y.png
dvha/resources/icons/iconfinder_Clipboard-Plan_379537_zoom.png
dvha/resources/icons/iconfinder_Close_1493281.png
dvha/resources/icons/iconfinder_Education-Filled_7_3672892.png
dvha/resources/icons/iconfinder_Open_1493293.png
dvha/resources/icons/iconfinder_Print_1493286.png
dvha/resources/icons/iconfinder_Save_1493294.png
dvha/resources/icons/iconfinder_Settings_1493289.png
dvha/resources/icons/iconfinder_Travel-Filled-07_3671983.png
dvha/resources/icons/iconfinder_User_Customers_1218712.png
dvha/resources/icons/iconfinder_User_Yuppie_3_1218716.png
dvha/resources/icons/iconfinder_csv_file_database_extension_data_3876336.png
dvha/resources/icons/iconfinder_data_115746_black_edit.png
dvha/resources/icons/iconfinder_icon-map_211858.png
dvha/resources/icons/iconfinder_import_4168538.png
dvha/resources/icons/iconfinder_ko-red_53948.png
dvha-0.9.7.dist-info/LICENSE.txt
dvha-0.9.7.dist-info/METADATA
dvha-0.9.7.dist-info/WHEEL
dvha-0.9.7.dist-info/entry_points.txt
dvha-0.9.7.dist-info/top_level.txt
dvha-0.9.7.dist-info/RECORD
