Metadata-Version: 2.1
Name: dvha
Version: 0.9.7
Summary: Create a database of DVHs, GUI with wxPython, plots with Bokeh
Home-page: https://github.com/cutright/DVH-Analytics
Author: Dan Cutright
Author-email: dan.cutright@gmail.com
License: BSD License
Download-URL: https://github.com/cutright/DVH-Analytics-Desktop/archive/master.zip
Keywords: dvh,radiation therapy,research,dicom,dicom-rt,bokeh,analytics,wxpython
Platform: UNKNOWN
Requires-Python: >3.5
Requires-Dist: dicompyler-core (>=0.5.5)
Requires-Dist: wxPython (>=4.1.1)
Requires-Dist: pypubsub
Requires-Dist: numpy
Requires-Dist: scipy
Requires-Dist: pydicom (>=1.4.0)
Requires-Dist: bokeh (<2.0.0,>=1.2.0)
Requires-Dist: psycopg2-binary
Requires-Dist: shapely[vectorized]
Requires-Dist: python-dateutil
Requires-Dist: statsmodels (>=0.8.0)
Requires-Dist: scikit-learn (>=0.21.0)
Requires-Dist: regressors
Requires-Dist: rapidfuzz
Requires-Dist: selenium
Requires-Dist: pandas (>=1.1.5)
Requires-Dist: scikit-image
Requires-Dist: dvha-mlca (>=0.2.3.post1)
